tool_anywhere_agent/__init__.py
tool_anywhere_agent/main.py
tool_anywhere_agent/prompt_builder.py
tool_anywhere_agent-0.0.2.dist-info/licenses/LICENSE
tool_anywhere_agent-0.0.2.dist-info/METADATA
tool_anywhere_agent-0.0.2.dist-info/WHEEL
tool_anywhere_agent-0.0.2.dist-info/top_level.txt
tool_anywhere_agent-0.0.2.dist-info/RECORD
