Metadata-Version: 2.4
Name: tool-anywhere-agent
Version: 0.0.2
Summary: A LangGraph-based agent for tool calling capabilities
Author: Mad Professor
Maintainer: Mad Professor
License: MIT License
Project-URL: Homepage, https://github.com/madprofessor42/tool_anywhere_agent
Project-URL: Repository, https://github.com/madprofessor42/tool_anywhere_agent
Project-URL: Documentation, https://github.com/madprofessor42/tool_anywhere_agent#readme
Project-URL: Issues, https://github.com/madprofessor42/tool_anywhere_agent/issues
Keywords: ai,langchain,langgraph,agent,tools,llm
Classifier: Development Status :: 3 - Alpha
Classifier: Intended Audience :: Developers
Classifier: License :: OSI Approved :: MIT License
Classifier: Operating System :: OS Independent
Classifier: Programming Language :: Python :: 3
Classifier: Programming Language :: Python :: 3.11
Classifier: Programming Language :: Python :: 3.12
Classifier: Topic :: Scientific/Engineering :: Artificial Intelligence
Classifier: Topic :: Software Development :: Libraries :: Python Modules
Requires-Python: >=3.11
License-File: LICENSE
Requires-Dist: langchain>=0.3.25
Requires-Dist: langchain-community>=0.3.25
Requires-Dist: langchain-openai>=0.3.22
Requires-Dist: langgraph>=0.4.8
Requires-Dist: pydantic>=2.0.0
Requires-Dist: python-dotenv>=1.0.0
Requires-Dist: typing-extensions>=4.0.0
Provides-Extra: dev
Requires-Dist: pytest>=7.0; extra == "dev"
Requires-Dist: pytest-cov>=4.0; extra == "dev"
Requires-Dist: black>=23.0; extra == "dev"
Requires-Dist: flake8>=6.0; extra == "dev"
Requires-Dist: mypy>=1.0; extra == "dev"
Requires-Dist: pre-commit>=3.0; extra == "dev"
Provides-Extra: docs
Requires-Dist: sphinx>=5.0; extra == "docs"
Requires-Dist: sphinx-rtd-theme>=1.0; extra == "docs"
Dynamic: license-file
